premier_league_api/__init__.py
premier_league_api/client.py
premier_league_api/competitions.py
premier_league_api/errors.py
premier_league_api/fixture.py
premier_league_api/gameweek.py
premier_league_api/meta_competitions.py
premier_league_api/player.py
premier_league_api/shared.py
premier_league_api-2.0.0.dist-info/METADATA
premier_league_api-2.0.0.dist-info/WHEEL
premier_league_api-2.0.0.dist-info/top_level.txt
premier_league_api-2.0.0.dist-info/zip-safe
premier_league_api-2.0.0.dist-info/RECORD
