Metadata-Version: 2.1
Name: premier-league-api
Version: 2.0.0
Summary: API for pulling Premier League Data
Home-page: https://github.com/Cyb3r-Jak3/premier_league_api
Author: Cyb3r-Jak3
Author-email: git@cyberjake.xyz
License: MPL 2.0
Download-URL: https://github.com/Cyb3r-Jak3/premier_league_api/releases/latest
Project-URL: Changelog, https://github.com/Cyb3r-Jak3/premier_league_api/blob/main/CHANGELOG.md
Project-URL: Issues, https://github.com/Cyb3r-Jak3/premier_league_api/issues
Keywords: premier league,REST,api client,REST API
Platform: UNKNOWN
Classifier: Development Status :: 5 - Production/Stable
Classifier: Intended Audience :: Developers
Classifier: License :: OSI Approved :: Mozilla Public License 2.0 (MPL 2.0)
Classifier: Natural Language :: English
Classifier: Programming Language :: Python :: 3 :: Only
Classifier: Programming Language :: Python :: 3
Classifier: Programming Language :: Python :: 3.8
Classifier: Programming Language :: Python :: 3.9
Classifier: Programming Language :: Python :: 3.10
Classifier: Programming Language :: Python :: Implementation :: CPython
Requires-Dist: cached-property (>=1.5.2)
Requires-Dist: requests (>=2.25.1)
